keysmith.py
keysmith-3.0.1.dist-info/LICENSE
keysmith-3.0.1.dist-info/METADATA
keysmith-3.0.1.dist-info/WHEEL
keysmith-3.0.1.dist-info/entry_points.txt
keysmith-3.0.1.dist-info/top_level.txt
keysmith-3.0.1.dist-info/RECORD
