Metadata-Version: 2.1
Name: keysmith
Version: 3.0.1
Summary: Passphrase Generator
Home-page: https://github.com/dmtucker/keysmith
Author: David Tucker
Author-email: david@tucker.name
License: BSD 3-Clause License
Keywords: diceware generator keygen passphrase password
Platform: UNKNOWN
Classifier: Development Status :: 7 - Inactive
Requires-Python: ~=3.5
